LICENSE.txt
MANIFEST.in
README.md
setup.cfg
setup.py
tokidoro/__init__.py
tokidoro/audio.json
tokidoro/cli.py
tokidoro/config.json
tokidoro.egg-info/PKG-INFO
tokidoro.egg-info/SOURCES.txt
tokidoro.egg-info/dependency_links.txt
tokidoro.egg-info/entry_points.txt
tokidoro.egg-info/not-zip-safe
tokidoro.egg-info/requires.txt
tokidoro.egg-info/top_level.txt
tokidoro/sounds/amaterasu.mp3
tokidoro/sounds/naruto_notification.mp3
tokidoro/sounds/notification.mp3
tokidoro/sounds/notification.wav
tokidoro/sounds/peace_peace.mp3