Metadata-Version: 2.1
Name: tokidoro
Version: 0.1
Summary: Pomodoro CLI
Home-page: https://github.com/nearlynithin/tokidoro
Author: Nithin Umesh
Author-email: nearlynithin@example.com
License: MIT
Platform: UNKNOWN
License-File: LICENSE.txt
